README.md
setup.py
guandu/__init__.py
guandu/ident_number.py
guandu/mongo.py
guandu/mysql.py
guandu/randomer.py
guandu/redis.py
guandu/retry.py
guandu/thd_async.py
guandu/timer.py
guandu.egg-info/PKG-INFO
guandu.egg-info/SOURCES.txt
guandu.egg-info/dependency_links.txt
guandu.egg-info/entry_points.txt
guandu.egg-info/top_level.txt
guandu.egg-info/zip-safe
test/test_decorator.py
test/test_mysql_cmd.py