Metadata-Version: 1.1
Name: guandu
Version: 1.1.0.9
Summary: base code for project
Home-page: http://test.com
Author: feikong
Author-email: feikong@shouxin168.com
License: UNKNOWN
Keywords: guandu
Platform: UNKNOWN
Classifier: License :: OSI Approved :: MIT License
Classifier: Programming Language :: Python
Classifier: Intended Audience :: Developers
Classifier: Operating System :: OS Independent
